pns/__init__.py
pns/base.py
pns/pss.py
pns/transform.py
pns/util.py
pnspy-0.2.2.dist-info/licenses/LICENSE
pnspy-0.2.2.dist-info/METADATA
pnspy-0.2.2.dist-info/WHEEL
pnspy-0.2.2.dist-info/top_level.txt
pnspy-0.2.2.dist-info/RECORD
